{
  "colors": {
    "blue": {
      "0": {
        "value": "#F2F7FD",
        "type": "color",
        "description": "blue/0"
      },
      "10": {
        "value": "#BFD9F3",
        "type": "color",
        "description": "blue/10"
      },
      "20": {
        "value": "#80B2E8",
        "type": "color",
        "description": "blue/20"
      },
      "30": {
        "value": "#408BDD",
        "type": "color",
        "description": "blue/30"
      },
      "40": {
        "value": "#0065D1",
        "type": "color",
        "description": "blue/40"
      },
      "50": {
        "value": "#0056B2",
        "type": "color",
        "description": "blue/50"
      },
      "60": {
        "value": "#004C9D",
        "type": "color",
        "description": "blue/60"
      }
    },
    "green": {
      "0": {
        "value": "#F4FBF6",
        "type": "color",
        "description": "green/0"
      },
      "10": {
        "value": "#C8ECD0",
        "type": "color",
        "description": "green/10"
      },
      "20": {
        "value": "#91D8A0",
        "type": "color",
        "description": "green/20"
      },
      "30": {
        "value": "#5AC571",
        "type": "color",
        "description": "green/30"
      },
      "40": {
        "value": "#23B242",
        "type": "color",
        "description": "green/40"
      },
      "50": {
        "value": "#1E9738",
        "type": "color",
        "description": "green/50"
      },
      "60": {
        "value": "#1A8531",
        "type": "color",
        "description": "green/60"
      }
    },
    "lightBlue": {
      "0": {
        "value": "#F2FBFC",
        "type": "color",
        "description": "lightBlue/0"
      },
      "10": {
        "value": "#C0EBF1",
        "type": "color",
        "description": "lightBlue/10"
      },
      "20": {
        "value": "#80D7E2",
        "type": "color",
        "description": "lightBlue/20"
      },
      "30": {
        "value": "#41C2D4",
        "type": "color",
        "description": "lightBlue/30"
      },
      "40": {
        "value": "#02AEC5",
        "type": "color",
        "description": "lightBlue/40"
      },
      "50": {
        "value": "#0294A7",
        "type": "color",
        "description": "lightBlue/50"
      },
      "60": {
        "value": "#018294",
        "type": "color",
        "description": "lightBlue/60"
      }
    },
    "orange": {
      "0": {
        "value": "#FFFBF4",
        "type": "color",
        "description": "orange/0"
      },
      "10": {
        "value": "#FDE9C8",
        "type": "color",
        "description": "orange/10"
      },
      "20": {
        "value": "#FAD391",
        "type": "color",
        "description": "orange/20"
      },
      "30": {
        "value": "#F8BC5A",
        "type": "color",
        "description": "orange/30"
      },
      "40": {
        "value": "#F5A623",
        "type": "color",
        "description": "orange/40"
      },
      "50": {
        "value": "#D08D1E",
        "type": "color",
        "description": "orange/50"
      },
      "60": {
        "value": "#B87C1A",
        "type": "color",
        "description": "orange/60"
      }
    },
    "red": {
      "0": {
        "value": "#FEF5F4",
        "type": "color",
        "description": "red/0"
      },
      "10": {
        "value": "#F8CBCA",
        "type": "color",
        "description": "red/10"
      },
      "20": {
        "value": "#F29695",
        "type": "color",
        "description": "red/20"
      },
      "30": {
        "value": "#EB6261",
        "type": "color",
        "description": "red/30"
      },
      "40": {
        "value": "#E42E2C",
        "type": "color",
        "description": "red/40"
      },
      "50": {
        "value": "#C22725",
        "type": "color",
        "description": "red/50"
      },
      "60": {
        "value": "#AB2221",
        "type": "color",
        "description": "red/60"
      }
    },
    "gold": {
      "0": {
        "value": "#FBFAF2",
        "type": "color",
        "description": "gold/0"
      },
      "10": {
        "value": "#EDE6BF",
        "type": "color",
        "description": "gold/10"
      },
      "20": {
        "value": "#DBCC80",
        "type": "color",
        "description": "gold/20"
      },
      "30": {
        "value": "#C9B340",
        "type": "color",
        "description": "gold/30"
      },
      "40": {
        "value": "#B79A00",
        "type": "color",
        "description": "gold/40"
      },
      "50": {
        "value": "#9C8300",
        "type": "color",
        "description": "gold/50"
      },
      "60": {
        "value": "#897400",
        "type": "color",
        "description": "gold/60"
      }
    },
    "yellow": {
      "0": {
        "value": "#FEFDF4",
        "type": "color",
        "description": "yellow/0"
      },
      "10": {
        "value": "#FBF5CA",
        "type": "color",
        "description": "yellow/10"
      },
      "20": {
        "value": "#F7EA95",
        "type": "color",
        "description": "yellow/20"
      },
      "30": {
        "value": "#F3E061",
        "type": "color",
        "description": "yellow/30"
      },
      "40": {
        "value": "#EFD52C",
        "type": "color",
        "description": "yellow/40"
      },
      "50": {
        "value": "#CBB525",
        "type": "color",
        "description": "yellow/50"
      },
      "60": {
        "value": "#B3A021",
        "type": "color",
        "description": "yellow/60"
      }
    },
    "lime": {
      "0": {
        "value": "#FAFEF5",
        "type": "color",
        "description": "lime/0"
      },
      "10": {
        "value": "#E8F9CD",
        "type": "color",
        "description": "lime/10"
      },
      "20": {
        "value": "#D1F39A",
        "type": "color",
        "description": "lime/20"
      },
      "30": {
        "value": "#BAEC68",
        "type": "color",
        "description": "lime/30"
      },
      "40": {
        "value": "#A3E635",
        "type": "color",
        "description": "lime/40"
      },
      "50": {
        "value": "#8BC32D",
        "type": "color",
        "description": "lime/50"
      },
      "60": {
        "value": "#7AAC28",
        "type": "color",
        "description": "lime/60"
      }
    },
    "teal": {
      "0": {
        "value": "#F3FBFA",
        "type": "color",
        "description": "teal/0"
      },
      "10": {
        "value": "#C4EDE6",
        "type": "color",
        "description": "teal/10"
      },
      "20": {
        "value": "#88DBCE",
        "type": "color",
        "description": "teal/20"
      },
      "30": {
        "value": "#4DCAB5",
        "type": "color",
        "description": "teal/30"
      },
      "40": {
        "value": "#12B89C",
        "type": "color",
        "description": "teal/40"
      },
      "50": {
        "value": "#0F9C85",
        "type": "color",
        "description": "teal/50"
      },
      "60": {
        "value": "#0E8A75",
        "type": "color",
        "description": "teal/60"
      }
    },
    "purple": {
      "0": {
        "value": "#F7F2FD",
        "type": "color",
        "description": "purple/0"
      },
      "10": {
        "value": "#D7BFF3",
        "type": "color",
        "description": "purple/10"
      },
      "20": {
        "value": "#AE80E8",
        "type": "color",
        "description": "purple/20"
      },
      "30": {
        "value": "#8640DD",
        "type": "color",
        "description": "purple/30"
      },
      "40": {
        "value": "#5E00D1",
        "type": "color",
        "description": "purple/40"
      },
      "50": {
        "value": "#5000B2",
        "type": "color",
        "description": "purple/50"
      },
      "60": {
        "value": "#46009D",
        "type": "color",
        "description": "purple/60"
      }
    },
    "black": {
      "5": {
        "value": "#0000000D",
        "type": "color",
        "description": "black/5"
      },
      "10": {
        "value": "#0000001A",
        "type": "color",
        "description": "black/10"
      },
      "20": {
        "value": "#00000033",
        "type": "color",
        "description": "black/20"
      },
      "30": {
        "value": "#0000004D",
        "type": "color",
        "description": "black/30"
      },
      "40": {
        "value": "#00000066",
        "type": "color",
        "description": "black/40"
      },
      "50": {
        "value": "#00000080",
        "type": "color",
        "description": "black/50"
      },
      "60": {
        "value": "#00000099",
        "type": "color",
        "description": "black/60"
      },
      "70": {
        "value": "#000000B3",
        "type": "color",
        "description": "black/70"
      },
      "80": {
        "value": "#000000CC",
        "type": "color",
        "description": "black/80"
      },
      "90": {
        "value": "#000000E6",
        "type": "color",
        "description": "black/90"
      },
      "100": {
        "value": "#000000",
        "type": "color",
        "description": "black/100"
      }
    },
    "gray": {
      "0": {
        "value": "#FAFAFA",
        "type": "color",
        "description": "gray/0"
      },
      "5": {
        "value": "#F3F3F3",
        "type": "color",
        "description": "gray/5"
      },
      "10": {
        "value": "#E7E7E8",
        "type": "color",
        "description": "gray/10"
      },
      "15": {
        "value": "#DBDBDC",
        "type": "color",
        "description": "gray/15"
      },
      "20": {
        "value": "#CFCFD1",
        "type": "color",
        "description": "gray/20"
      },
      "25": {
        "value": "#C2C3C5",
        "type": "color",
        "description": "gray/25"
      },
      "30": {
        "value": "#B6B8B9",
        "type": "color",
        "description": "gray/30"
      },
      "35": {
        "value": "#AAACAE",
        "type": "color",
        "description": "gray/35"
      },
      "40": {
        "value": "#9EA0A2",
        "type": "color",
        "description": "gray/40"
      },
      "45": {
        "value": "#929497",
        "type": "color",
        "description": "gray/45"
      },
      "50": {
        "value": "#86888B",
        "type": "color",
        "description": "gray/50"
      },
      "55": {
        "value": "#7A7C7F",
        "type": "color",
        "description": "gray/55"
      },
      "60": {
        "value": "#6E7074",
        "type": "color",
        "description": "gray/60"
      },
      "65": {
        "value": "#626468",
        "type": "color",
        "description": "gray/65"
      },
      "70": {
        "value": "#56585D",
        "type": "color",
        "description": "gray/70"
      },
      "75": {
        "value": "#4A4D51",
        "type": "color",
        "description": "gray/75"
      },
      "80": {
        "value": "#3D4145",
        "type": "color",
        "description": "gray/80"
      },
      "85": {
        "value": "#31353A",
        "type": "color",
        "description": "gray/85"
      },
      "90": {
        "value": "#25292E",
        "type": "color",
        "description": "gray/90"
      },
      "95": {
        "value": "#191D23",
        "type": "color",
        "description": "gray/95"
      },
      "100": {
        "value": "#0D1117",
        "type": "color",
        "description": "gray/100"
      }
    },
    "white": {
      "5": {
        "value": "#FFFFFF0D",
        "type": "color",
        "description": "white/5"
      },
      "10": {
        "value": "#FFFFFF1A",
        "type": "color",
        "description": "white/10"
      },
      "20": {
        "value": "#FFFFFF33",
        "type": "color",
        "description": "white/20"
      },
      "30": {
        "value": "#FFFFFF4D",
        "type": "color",
        "description": "white/30"
      },
      "40": {
        "value": "#FFFFFF66",
        "type": "color",
        "description": "white/40"
      },
      "50": {
        "value": "#FFFFFF80",
        "type": "color",
        "description": "white/50"
      },
      "60": {
        "value": "#FFFFFF99",
        "type": "color",
        "description": "white/60"
      },
      "70": {
        "value": "#FFFFFFB3",
        "type": "color",
        "description": "white/70"
      },
      "80": {
        "value": "#FFFFFFCC",
        "type": "color",
        "description": "white/80"
      },
      "90": {
        "value": "#FFFFFFE6",
        "type": "color",
        "description": "white/90"
      },
      "100": {
        "value": "#FFFFFF",
        "type": "color",
        "description": "white/100"
      }
    },
    "misc": {
      "shimmer": {
        "value": "linear-gradient(90deg, rgba($gray.5, $opacity.0) 0%, $gray.5 50%, rgba($gray.5, $opacity.0) 100%)",
        "type": "color",
        "description": "misc/shimmer"
      },
      "labelBg": {
        "value": "linear-gradient(180deg, #00000000 46.88%, #ffffff 46.88%)",
        "type": "color",
        "description": "misc/labelBg"
      },
      "transparent": {
        "value": "#00000000",
        "type": "color",
        "description": "misc/transparent"
      }
    },
    "opacity": {
      "0": {
        "value": "0%",
        "type": "opacity"
      },
      "5": {
        "value": "5%",
        "type": "opacity"
      },
      "10": {
        "value": "10%",
        "type": "opacity"
      },
      "15": {
        "value": "15%",
        "type": "opacity"
      },
      "20": {
        "value": "20%",
        "type": "opacity"
      },
      "25": {
        "value": "25%",
        "type": "opacity"
      },
      "30": {
        "value": "30%",
        "type": "opacity"
      },
      "35": {
        "value": "35%",
        "type": "opacity"
      },
      "40": {
        "value": "40%",
        "type": "opacity"
      },
      "45": {
        "value": "45%",
        "type": "opacity"
      },
      "50": {
        "value": "50%",
        "type": "opacity"
      },
      "55": {
        "value": "55%",
        "type": "opacity"
      },
      "60": {
        "value": "60%",
        "type": "opacity"
      },
      "65": {
        "value": "65%",
        "type": "opacity"
      },
      "70": {
        "value": "70%",
        "type": "opacity"
      },
      "75": {
        "value": "75%",
        "type": "opacity"
      },
      "80": {
        "value": "80%",
        "type": "opacity"
      },
      "85": {
        "value": "85%",
        "type": "opacity"
      },
      "90": {
        "value": "90%",
        "type": "opacity"
      },
      "95": {
        "value": "95%",
        "type": "opacity"
      },
      "100": {
        "value": "100%",
        "type": "opacity"
      }
    }
  },
  "semantics: light": {
    "fg": {
      "default": {
        "value": "{gray.100}",
        "type": "color",
        "description": "gray/100"
      },
      "subtle": {
        "value": "{gray.70}",
        "type": "color",
        "description": "gray/70"
      },
      "muted": {
        "value": "{gray.40}",
        "type": "color",
        "description": "gray/40"
      },
      "onEmphasis": {
        "value": "{white.100}",
        "type": "color",
        "description": "white/100"
      },
      "accent": {
        "value": "{blue.50}",
        "type": "color",
        "description": "blue/50"
      },
      "success": {
        "value": "{green.50}",
        "type": "color",
        "description": "green/50"
      },
      "warning": {
        "value": "{orange.50}",
        "type": "color",
        "description": "orange/50"
      },
      "danger": {
        "value": "{red.50}",
        "type": "color",
        "description": "red/50"
      }
    },
    "bg": {
      "default": {
        "value": "{white.100}",
        "type": "color",
        "description": "white/100"
      },
      "defaultAlpha": {
        "value": "rgba({gray.50},{opacity.5})",
        "type": "color",
        "description": "rgba(gray/50, 0.05)"
      },
      "subtle": {
        "value": "{gray.0}",
        "type": "color",
        "description": "gray/0"
      },
      "subtleAlpha": {
        "value": "rgba({gray.80},{opacity.10})",
        "type": "color",
        "description": "rgba(gray/80, 0.1)"
      },
      "muted": {
        "value": "{gray.5}",
        "type": "color",
        "description": "gray/5"
      },
      "inactive": {
        "value": "{gray.20}",
        "type": "color",
        "description": "gray/20"
      },
      "emphasis": {
        "value": "{gray.100}",
        "type": "color",
        "description": "gray/100"
      },
      "emphasisAlpha": {
        "value": "rgba({gray.0},{opacity.5})",
        "type": "color",
        "description": "rgba(gray/0, 0.05)"
      },
      "emphasisSubtle": {
        "value": "{gray.95}",
        "type": "color",
        "description": "gray/95"
      },
      "emphasisAlphaSubtle": {
        "value": "rgba({gray.0},{opacity.10})",
        "type": "color",
        "description": "rgba(gray/0, 0.1)"
      },
      "accent": {
        "value": "{blue.0}",
        "type": "color",
        "description": "blue/0"
      },
      "accentEmphasis": {
        "value": "{blue.40}",
        "type": "color",
        "description": "blue/40"
      },
      "success": {
        "value": "{green.0}",
        "type": "color",
        "description": "green/0"
      },
      "successEmphasis": {
        "value": "{green.40}",
        "type": "color",
        "description": "green/40"
      },
      "warning": {
        "value": "{orange.0}",
        "type": "color",
        "description": "orange/0"
      },
      "warningEmphasis": {
        "value": "{orange.40}",
        "type": "color",
        "description": "orange/40"
      },
      "danger": {
        "value": "{red.0}",
        "type": "color",
        "description": "red/0"
      },
      "dangerEmphasis": {
        "value": "{red.40}",
        "type": "color",
        "description": "red/40"
      }
    },
    "border": {
      "default": {
        "value": "{gray.15}",
        "type": "color",
        "description": "gray/15"
      },
      "defaultAlpha": {
        "value": "rgba({gray.100},{opacity.5})",
        "type": "color",
        "description": "rgba(gray/100, 0.05)"
      },
      "subtle": {
        "value": "{gray.20}",
        "type": "color",
        "description": "gray/20"
      },
      "subtleAlpha": {
        "value": "rgba({gray.100},{opacity.10})",
        "type": "color",
        "description": "rgba(gray/100, 0.1)"
      },
      "muted": {
        "value": "{gray.10}",
        "type": "color",
        "description": "gray/10"
      },
      "onEmphasis": {
        "value": "{gray.70}",
        "type": "color",
        "description": "gray/70"
      },
      "onEmphasisAlpha": {
        "value": "rgba({gray.0},{opacity.5})",
        "type": "color",
        "description": "rgba(gray/0, 0.05)"
      },
      "onEmphasisAlphaSubtle": {
        "value": "rgba({gray.0},{opacity.10})",
        "type": "color",
        "description": "rgba(gray/0, 0.1)"
      },
      "accent": {
        "value": "{blue.10}",
        "type": "color",
        "description": "blue/10"
      },
      "accentEmphasis": {
        "value": "{blue.40}",
        "type": "color",
        "description": "blue/40"
      },
      "success": {
        "value": "{green.10}",
        "type": "color",
        "description": "green/10"
      },
      "successEmphasis": {
        "value": "{green.40}",
        "type": "color",
        "description": "green/40"
      },
      "warning": {
        "value": "{orange.10}",
        "type": "color",
        "description": "orange/10"
      },
      "warningEmphasis": {
        "value": "{orange.40}",
        "type": "color",
        "description": "orange/40"
      },
      "danger": {
        "value": "{red.10}",
        "type": "color",
        "description": "red/10"
      },
      "dangerEmphasis": {
        "value": "{red.40}",
        "type": "color",
        "description": "red/40"
      }
    },
    "shadow": {
      "small": {
        "value": [
          {
            "color": "#0d11170d",
            "type": "dropShadow",
            "x": 0,
            "y": 1,
            "blur": 2,
            "spread": 0
          },
          {
            "color": "#0d11171a",
            "type": "dropShadow",
            "x": 0,
            "y": 1,
            "blur": 3,
            "spread": 0
          }
        ],
        "type": "boxShadow"
      },
      "medium": {
        "value": [
          {
            "color": "#0d11170d",
            "type": "dropShadow",
            "x": 0,
            "y": 2,
            "blur": 4,
            "spread": 0
          },
          {
            "color": "#0d11171a",
            "type": "dropShadow",
            "x": 0,
            "y": 4,
            "blur": 6,
            "spread": -1
          }
        ],
        "type": "boxShadow"
      },
      "large": {
        "value": [
          {
            "color": "#0d11170d",
            "type": "dropShadow",
            "x": 0,
            "y": 4,
            "blur": 6,
            "spread": 0
          },
          {
            "color": "#0d11171a",
            "type": "dropShadow",
            "x": 0,
            "y": 10,
            "blur": 15,
            "spread": -3
          }
        ],
        "type": "boxShadow"
      },
      "xlarge": {
        "value": [
          {
            "color": "#0d11171a",
            "type": "dropShadow",
            "x": 0,
            "y": 16,
            "blur": 25,
            "spread": -2
          },
          {
            "color": "#0d11171a",
            "type": "dropShadow",
            "x": 0,
            "y": 8,
            "blur": 10,
            "spread": -2
          },
          {
            "color": "#0d111726",
            "type": "dropShadow",
            "x": 0,
            "y": 0,
            "blur": 1,
            "spread": 0
          }
        ],
        "type": "boxShadow"
      },
      "2xlarge": {
        "value": {
          "color": "#0d111740",
          "type": "dropShadow",
          "x": 0,
          "y": 20,
          "blur": 40,
          "spread": -8
        },
        "type": "boxShadow"
      }
    },
    "additional": {
      "largeTop": {
        "value": [
          {
            "color": "#0d11170d",
            "type": "dropShadow",
            "x": 0,
            "y": -4,
            "blur": 6,
            "spread": 0
          },
          {
            "color": "#0d11171a",
            "type": "dropShadow",
            "x": 0,
            "y": -10,
            "blur": 15,
            "spread": -3
          }
        ],
        "type": "boxShadow"
      },
      "largeLeft": {
        "value": [
          {
            "color": "#0d11170d",
            "type": "dropShadow",
            "x": -4,
            "y": 0,
            "blur": 6,
            "spread": 0
          },
          {
            "color": "#0d11171a",
            "type": "dropShadow",
            "x": -10,
            "y": 0,
            "blur": 15,
            "spread": -3
          }
        ],
        "type": "boxShadow"
      },
      "largeRight": {
        "value": [
          {
            "color": "#0d11170d",
            "type": "dropShadow",
            "x": 4,
            "y": 0,
            "blur": 6,
            "spread": 0
          },
          {
            "color": "#0d11171a",
            "type": "dropShadow",
            "x": 10,
            "y": 0,
            "blur": 15,
            "spread": -3
          }
        ],
        "type": "boxShadow"
      },
      "onEmphasis": {
        "value": [
          {
            "color": "#0d111726",
            "type": "dropShadow",
            "x": 0,
            "y": 4,
            "blur": 6,
            "spread": -2
          },
          {
            "color": "#0d111759",
            "type": "dropShadow",
            "x": 0,
            "y": 10,
            "blur": 15,
            "spread": -3
          }
        ],
        "type": "boxShadow"
      },
      "onEmphasisDarker": {
        "value": [
          {
            "color": "#000000a6",
            "type": "dropShadow",
            "x": 0,
            "y": 4,
            "blur": 6,
            "spread": -2
          },
          {
            "color": "#000000d9",
            "type": "dropShadow",
            "x": 0,
            "y": 10,
            "blur": 15,
            "spread": -3
          }
        ],
        "type": "boxShadow"
      }
    },
    "roles": {
      "accent": {
        "value": [
          {
            "color": "#0065d10d",
            "type": "dropShadow",
            "x": 0,
            "y": 4,
            "blur": 6,
            "spread": -2
          },
          {
            "color": "#0065d11a",
            "type": "dropShadow",
            "x": 0,
            "y": 10,
            "blur": 15,
            "spread": -3
          }
        ],
        "type": "boxShadow"
      },
      "success": {
        "value": [
          {
            "color": "#23b2420d",
            "type": "dropShadow",
            "x": 0,
            "y": 4,
            "blur": 6,
            "spread": -2
          },
          {
            "color": "#23b2421a",
            "type": "dropShadow",
            "x": 0,
            "y": 10,
            "blur": 15,
            "spread": -3
          }
        ],
        "type": "boxShadow"
      },
      "warning": {
        "value": [
          {
            "color": "#f5a6230d",
            "type": "dropShadow",
            "x": 0,
            "y": 4,
            "blur": 6,
            "spread": -2
          },
          {
            "color": "#f5a6230d",
            "type": "dropShadow",
            "x": 0,
            "y": 10,
            "blur": 15,
            "spread": -3
          }
        ],
        "type": "boxShadow"
      },
      "danger": {
        "value": [
          {
            "color": "#e42e2c0d",
            "type": "dropShadow",
            "x": 0,
            "y": 4,
            "blur": 6,
            "spread": -2
          },
          {
            "color": "#e42e2c1a",
            "type": "dropShadow",
            "x": 0,
            "y": 10,
            "blur": 15,
            "spread": -3
          }
        ],
        "type": "boxShadow"
      }
    },
    "outline": {
      "default": {
        "value": {
          "color": "#9ea0a21a",
          "type": "dropShadow",
          "x": 0,
          "y": 0,
          "blur": 0,
          "spread": 4
        },
        "type": "boxShadow"
      },
      "defaultOnEmphasis": {
        "value": {
          "color": "#9ea0a24d",
          "type": "dropShadow",
          "x": 0,
          "y": 0,
          "blur": 0,
          "spread": 4
        },
        "type": "boxShadow"
      },
      "accent": {
        "value": {
          "color": "#0065d11a",
          "type": "dropShadow",
          "x": 0,
          "y": 0,
          "blur": 0,
          "spread": 4
        },
        "type": "boxShadow"
      },
      "accentOnEmphasis": {
        "value": {
          "color": "#0065d14d",
          "type": "dropShadow",
          "x": 0,
          "y": 0,
          "blur": 0,
          "spread": 4
        },
        "type": "boxShadow"
      },
      "success": {
        "value": {
          "color": "#23b2421a",
          "type": "dropShadow",
          "x": 0,
          "y": 0,
          "blur": 0,
          "spread": 4
        },
        "type": "boxShadow"
      },
      "successOnEmphasis": {
        "value": {
          "color": "#23b2424d",
          "type": "dropShadow",
          "x": 0,
          "y": 0,
          "blur": 0,
          "spread": 4
        },
        "type": "boxShadow"
      },
      "warning": {
        "value": {
          "color": "#f5a6231a",
          "type": "dropShadow",
          "x": 0,
          "y": 0,
          "blur": 0,
          "spread": 4
        },
        "type": "boxShadow"
      },
      "warningOnEmphasis": {
        "value": {
          "color": "#f5a6234d",
          "type": "dropShadow",
          "x": 0,
          "y": 0,
          "blur": 0,
          "spread": 4
        },
        "type": "boxShadow"
      },
      "danger": {
        "value": {
          "color": "#e42e2c1a",
          "type": "dropShadow",
          "x": 0,
          "y": 0,
          "blur": 0,
          "spread": 4
        },
        "type": "boxShadow"
      },
      "dangerOnEmphasis": {
        "value": {
          "color": "#e42e2c4d",
          "type": "dropShadow",
          "x": 0,
          "y": 0,
          "blur": 0,
          "spread": 4
        },
        "type": "boxShadow"
      }
    }
  },
  "$themes": [],
  "$metadata": {
    "tokenSetOrder": [
      "colors",
      "semantics: light"
    ]
  }
}